{
  "Type": "hooks",
  "Name": "npm-binary-releaser",
  "LatestRelease": "1.2.3",
  "Versions": {
    "1.0.0": {
      "CreatedAt": "2022-05-26T17:26:57Z",
      "Assets": [
        {
          "FileName": "hooks-npm-binary-releaser_v1.0.0_darwin_amd64",
          "URL": "https://github.com/go-semantic-release/hooks-npm-binary-releaser/releases/download/v1.0.0/hooks-npm-binary-releaser_v1.0.0_darwin_amd64",
          "OS": "darwin",
          "Arch": "amd64",
          "Checksum": "2ee71198fce0f7b51c14d8a79d51136794375496d2285f51bff79a6cad8fd026"
        },
        {
          "FileName": "hooks-npm-binary-releaser_v1.0.0_darwin_arm64",
          "URL": "https://github.com/go-semantic-release/hooks-npm-binary-releaser/releases/download/v1.0.0/hooks-npm-binary-releaser_v1.0.0_darwin_arm64",
          "OS": "darwin",
          "Arch": "arm64",
          "Checksum": "a4aa38710759e700686bba96188c98c3b4676b802ee6845c847c7144674a60fe"
        },
        {
          "FileName": "hooks-npm-binary-releaser_v1.0.0_linux_amd64",
          "URL": "https://github.com/go-semantic-release/hooks-npm-binary-releaser/releases/download/v1.0.0/hooks-npm-binary-releaser_v1.0.0_linux_amd64",
          "OS": "linux",
          "Arch": "amd64",
          "Checksum": "62b28e62c2fd4f7986fc6ae7693fe33a76eaaba06b3637db21a75e7446ffdd10"
        },
        {
          "FileName": "hooks-npm-binary-releaser_v1.0.0_linux_arm",
          "URL": "https://github.com/go-semantic-release/hooks-npm-binary-releaser/releases/download/v1.0.0/hooks-npm-binary-releaser_v1.0.0_linux_arm",
          "OS": "linux",
          "Arch": "arm",
          "Checksum": "b82381b2f2ea96257c7c5347dfd378a25de0fb38239e4f86bfe3ba96767d6e27"
        },
        {
          "FileName": "hooks-npm-binary-releaser_v1.0.0_linux_arm64",
          "URL": "https://github.com/go-semantic-release/hooks-npm-binary-releaser/releases/download/v1.0.0/hooks-npm-binary-releaser_v1.0.0_linux_arm64",
          "OS": "linux",
          "Arch": "arm64",
          "Checksum": "23b0f0d253d41e10aa328c39eb99d87667fc0d0f8314563be3b39f8cd159b743"
        }
      ]
    },
    "1.1.0": {
      "CreatedAt": "2022-05-26T17:44:05Z",
      "Assets": [
        {
          "FileName": "hooks-npm-binary-releaser_v1.1.0_darwin_amd64",
          "URL": "https://github.com/go-semantic-release/hooks-npm-binary-releaser/releases/download/v1.1.0/hooks-npm-binary-releaser_v1.1.0_darwin_amd64",
          "OS": "darwin",
          "Arch": "amd64",
          "Checksum": ""
        },
        {
          "FileName": "hooks-npm-binary-releaser_v1.1.0_darwin_arm64",
          "URL": "https://github.com/go-semantic-release/hooks-npm-binary-releaser/releases/download/v1.1.0/hooks-npm-binary-releaser_v1.1.0_darwin_arm64",
          "OS": "darwin",
          "Arch": "arm64",
          "Checksum": ""
        },
        {
          "FileName": "hooks-npm-binary-releaser_v1.1.0_linux_amd64",
          "URL": "https://github.com/go-semantic-release/hooks-npm-binary-releaser/releases/download/v1.1.0/hooks-npm-binary-releaser_v1.1.0_linux_amd64",
          "OS": "linux",
          "Arch": "amd64",
          "Checksum": ""
        },
        {
          "FileName": "hooks-npm-binary-releaser_v1.1.0_linux_arm",
          "URL": "https://github.com/go-semantic-release/hooks-npm-binary-releaser/releases/download/v1.1.0/hooks-npm-binary-releaser_v1.1.0_linux_arm",
          "OS": "linux",
          "Arch": "arm",
          "Checksum": ""
        },
        {
          "FileName": "hooks-npm-binary-releaser_v1.1.0_linux_arm64",
          "URL": "https://github.com/go-semantic-release/hooks-npm-binary-releaser/releases/download/v1.1.0/hooks-npm-binary-releaser_v1.1.0_linux_arm64",
          "OS": "linux",
          "Arch": "arm64",
          "Checksum": ""
        },
        {
          "FileName": "hooks-npm-binary-releaser_v1.1.0_windows_amd64.exe",
          "URL": "https://github.com/go-semantic-release/hooks-npm-binary-releaser/releases/download/v1.1.0/hooks-npm-binary-releaser_v1.1.0_windows_amd64.exe",
          "OS": "windows",
          "Arch": "amd64",
          "Checksum": ""
        }
      ]
    },
    "1.1.1": {
      "CreatedAt": "2022-05-26T18:06:57Z",
      "Assets": [
        {
          "FileName": "hooks-npm-binary-releaser_v1.1.1_darwin_amd64",
          "URL": "https://github.com/go-semantic-release/hooks-npm-binary-releaser/releases/download/v1.1.1/hooks-npm-binary-releaser_v1.1.1_darwin_amd64",
          "OS": "darwin",
          "Arch": "amd64",
          "Checksum": ""
        },
        {
          "FileName": "hooks-npm-binary-releaser_v1.1.1_darwin_arm64",
          "URL": "https://github.com/go-semantic-release/hooks-npm-binary-releaser/releases/download/v1.1.1/hooks-npm-binary-releaser_v1.1.1_darwin_arm64",
          "OS": "darwin",
          "Arch": "arm64",
          "Checksum": ""
        },
        {
          "FileName": "hooks-npm-binary-releaser_v1.1.1_linux_amd64",
          "URL": "https://github.com/go-semantic-release/hooks-npm-binary-releaser/releases/download/v1.1.1/hooks-npm-binary-releaser_v1.1.1_linux_amd64",
          "OS": "linux",
          "Arch": "amd64",
          "Checksum": ""
        },
        {
          "FileName": "hooks-npm-binary-releaser_v1.1.1_linux_arm",
          "URL": "https://github.com/go-semantic-release/hooks-npm-binary-releaser/releases/download/v1.1.1/hooks-npm-binary-releaser_v1.1.1_linux_arm",
          "OS": "linux",
          "Arch": "arm",
          "Checksum": ""
        },
        {
          "FileName": "hooks-npm-binary-releaser_v1.1.1_linux_arm64",
          "URL": "https://github.com/go-semantic-release/hooks-npm-binary-releaser/releases/download/v1.1.1/hooks-npm-binary-releaser_v1.1.1_linux_arm64",
          "OS": "linux",
          "Arch": "arm64",
          "Checksum": ""
        },
        {
          "FileName": "hooks-npm-binary-releaser_v1.1.1_windows_amd64.exe",
          "URL": "https://github.com/go-semantic-release/hooks-npm-binary-releaser/releases/download/v1.1.1/hooks-npm-binary-releaser_v1.1.1_windows_amd64.exe",
          "OS": "windows",
          "Arch": "amd64",
          "Checksum": ""
        }
      ]
    },
    "1.2.0": {
      "CreatedAt": "2022-05-26T19:29:52Z",
      "Assets": [
        {
          "FileName": "hooks-npm-binary-releaser_v1.2.0_darwin_amd64",
          "URL": "https://github.com/go-semantic-release/hooks-npm-binary-releaser/releases/download/v1.2.0/hooks-npm-binary-releaser_v1.2.0_darwin_amd64",
          "OS": "darwin",
          "Arch": "amd64",
          "Checksum": ""
        },
        {
          "FileName": "hooks-npm-binary-releaser_v1.2.0_darwin_arm64",
          "URL": "https://github.com/go-semantic-release/hooks-npm-binary-releaser/releases/download/v1.2.0/hooks-npm-binary-releaser_v1.2.0_darwin_arm64",
          "OS": "darwin",
          "Arch": "arm64",
          "Checksum": ""
        },
        {
          "FileName": "hooks-npm-binary-releaser_v1.2.0_linux_amd64",
          "URL": "https://github.com/go-semantic-release/hooks-npm-binary-releaser/releases/download/v1.2.0/hooks-npm-binary-releaser_v1.2.0_linux_amd64",
          "OS": "linux",
          "Arch": "amd64",
          "Checksum": ""
        },
        {
          "FileName": "hooks-npm-binary-releaser_v1.2.0_linux_arm",
          "URL": "https://github.com/go-semantic-release/hooks-npm-binary-releaser/releases/download/v1.2.0/hooks-npm-binary-releaser_v1.2.0_linux_arm",
          "OS": "linux",
          "Arch": "arm",
          "Checksum": ""
        },
        {
          "FileName": "hooks-npm-binary-releaser_v1.2.0_linux_arm64",
          "URL": "https://github.com/go-semantic-release/hooks-npm-binary-releaser/releases/download/v1.2.0/hooks-npm-binary-releaser_v1.2.0_linux_arm64",
          "OS": "linux",
          "Arch": "arm64",
          "Checksum": ""
        },
        {
          "FileName": "hooks-npm-binary-releaser_v1.2.0_windows_amd64.exe",
          "URL": "https://github.com/go-semantic-release/hooks-npm-binary-releaser/releases/download/v1.2.0/hooks-npm-binary-releaser_v1.2.0_windows_amd64.exe",
          "OS": "windows",
          "Arch": "amd64",
          "Checksum": ""
        }
      ]
    },
    "1.2.1": {
      "CreatedAt": "2022-05-26T19:32:15Z",
      "Assets": [
        {
          "FileName": "hooks-npm-binary-releaser_v1.2.1_darwin_amd64",
          "URL": "https://github.com/go-semantic-release/hooks-npm-binary-releaser/releases/download/v1.2.1/hooks-npm-binary-releaser_v1.2.1_darwin_amd64",
          "OS": "darwin",
          "Arch": "amd64",
          "Checksum": "a2c45c43a0d6a606ab55dadac53195b933695e13309e7730dd96b97e88a8030a"
        },
        {
          "FileName": "hooks-npm-binary-releaser_v1.2.1_darwin_arm64",
          "URL": "https://github.com/go-semantic-release/hooks-npm-binary-releaser/releases/download/v1.2.1/hooks-npm-binary-releaser_v1.2.1_darwin_arm64",
          "OS": "darwin",
          "Arch": "arm64",
          "Checksum": "48946a6fe14f1cf0770724e1dc472acb1c36017e8b305524aa96a8619edcfc80"
        },
        {
          "FileName": "hooks-npm-binary-releaser_v1.2.1_linux_amd64",
          "URL": "https://github.com/go-semantic-release/hooks-npm-binary-releaser/releases/download/v1.2.1/hooks-npm-binary-releaser_v1.2.1_linux_amd64",
          "OS": "linux",
          "Arch": "amd64",
          "Checksum": "319632b7dfa901ff8cde76f1b3883cfae163b305a4f1e12895b96c6dead34508"
        },
        {
          "FileName": "hooks-npm-binary-releaser_v1.2.1_linux_arm",
          "URL": "https://github.com/go-semantic-release/hooks-npm-binary-releaser/releases/download/v1.2.1/hooks-npm-binary-releaser_v1.2.1_linux_arm",
          "OS": "linux",
          "Arch": "arm",
          "Checksum": "7d8b58de900d575a2dfda6b1e99bae664fcf1e97281eacc99ad0aa61bf964ca2"
        },
        {
          "FileName": "hooks-npm-binary-releaser_v1.2.1_linux_arm64",
          "URL": "https://github.com/go-semantic-release/hooks-npm-binary-releaser/releases/download/v1.2.1/hooks-npm-binary-releaser_v1.2.1_linux_arm64",
          "OS": "linux",
          "Arch": "arm64",
          "Checksum": "d8e27b95e740f99a847eedb02bde6dac1f6a96c7837eb614e77d2af99e3098ae"
        },
        {
          "FileName": "hooks-npm-binary-releaser_v1.2.1_windows_amd64.exe",
          "URL": "https://github.com/go-semantic-release/hooks-npm-binary-releaser/releases/download/v1.2.1/hooks-npm-binary-releaser_v1.2.1_windows_amd64.exe",
          "OS": "windows",
          "Arch": "amd64",
          "Checksum": "c78540c7d3953dfc02ee0af8b68f36b68be002aa891ed848b5a8ef909edc0750"
        }
      ]
    },
    "1.2.2": {
      "CreatedAt": "2022-05-26T19:40:18Z",
      "Assets": [
        {
          "FileName": "hooks-npm-binary-releaser_v1.2.2_darwin_amd64",
          "URL": "https://github.com/go-semantic-release/hooks-npm-binary-releaser/releases/download/v1.2.2/hooks-npm-binary-releaser_v1.2.2_darwin_amd64",
          "OS": "darwin",
          "Arch": "amd64",
          "Checksum": ""
        },
        {
          "FileName": "hooks-npm-binary-releaser_v1.2.2_darwin_arm64",
          "URL": "https://github.com/go-semantic-release/hooks-npm-binary-releaser/releases/download/v1.2.2/hooks-npm-binary-releaser_v1.2.2_darwin_arm64",
          "OS": "darwin",
          "Arch": "arm64",
          "Checksum": ""
        },
        {
          "FileName": "hooks-npm-binary-releaser_v1.2.2_linux_amd64",
          "URL": "https://github.com/go-semantic-release/hooks-npm-binary-releaser/releases/download/v1.2.2/hooks-npm-binary-releaser_v1.2.2_linux_amd64",
          "OS": "linux",
          "Arch": "amd64",
          "Checksum": ""
        },
        {
          "FileName": "hooks-npm-binary-releaser_v1.2.2_linux_arm",
          "URL": "https://github.com/go-semantic-release/hooks-npm-binary-releaser/releases/download/v1.2.2/hooks-npm-binary-releaser_v1.2.2_linux_arm",
          "OS": "linux",
          "Arch": "arm",
          "Checksum": ""
        },
        {
          "FileName": "hooks-npm-binary-releaser_v1.2.2_linux_arm64",
          "URL": "https://github.com/go-semantic-release/hooks-npm-binary-releaser/releases/download/v1.2.2/hooks-npm-binary-releaser_v1.2.2_linux_arm64",
          "OS": "linux",
          "Arch": "arm64",
          "Checksum": ""
        },
        {
          "FileName": "hooks-npm-binary-releaser_v1.2.2_windows_amd64.exe",
          "URL": "https://github.com/go-semantic-release/hooks-npm-binary-releaser/releases/download/v1.2.2/hooks-npm-binary-releaser_v1.2.2_windows_amd64.exe",
          "OS": "windows",
          "Arch": "amd64",
          "Checksum": ""
        }
      ]
    },
    "1.2.3": {
      "CreatedAt": "2022-05-27T07:10:14Z",
      "Assets": [
        {
          "FileName": "hooks-npm-binary-releaser_v1.2.3_darwin_amd64",
          "URL": "https://github.com/go-semantic-release/hooks-npm-binary-releaser/releases/download/v1.2.3/hooks-npm-binary-releaser_v1.2.3_darwin_amd64",
          "OS": "darwin",
          "Arch": "amd64",
          "Checksum": ""
        },
        {
          "FileName": "hooks-npm-binary-releaser_v1.2.3_darwin_arm64",
          "URL": "https://github.com/go-semantic-release/hooks-npm-binary-releaser/releases/download/v1.2.3/hooks-npm-binary-releaser_v1.2.3_darwin_arm64",
          "OS": "darwin",
          "Arch": "arm64",
          "Checksum": ""
        },
        {
          "FileName": "hooks-npm-binary-releaser_v1.2.3_linux_amd64",
          "URL": "https://github.com/go-semantic-release/hooks-npm-binary-releaser/releases/download/v1.2.3/hooks-npm-binary-releaser_v1.2.3_linux_amd64",
          "OS": "linux",
          "Arch": "amd64",
          "Checksum": ""
        },
        {
          "FileName": "hooks-npm-binary-releaser_v1.2.3_linux_arm",
          "URL": "https://github.com/go-semantic-release/hooks-npm-binary-releaser/releases/download/v1.2.3/hooks-npm-binary-releaser_v1.2.3_linux_arm",
          "OS": "linux",
          "Arch": "arm",
          "Checksum": ""
        },
        {
          "FileName": "hooks-npm-binary-releaser_v1.2.3_linux_arm64",
          "URL": "https://github.com/go-semantic-release/hooks-npm-binary-releaser/releases/download/v1.2.3/hooks-npm-binary-releaser_v1.2.3_linux_arm64",
          "OS": "linux",
          "Arch": "arm64",
          "Checksum": ""
        },
        {
          "FileName": "hooks-npm-binary-releaser_v1.2.3_windows_amd64.exe",
          "URL": "https://github.com/go-semantic-release/hooks-npm-binary-releaser/releases/download/v1.2.3/hooks-npm-binary-releaser_v1.2.3_windows_amd64.exe",
          "OS": "windows",
          "Arch": "amd64",
          "Checksum": ""
        }
      ]
    }
  }
}
